mServices/QueryBuilderService.py
mServices/ResponseService.py
mServices/ValidatorService.py
mServices/__init__.py
mServices/asgi.py
mServices/settings.py
mServices/urls.py
mServices/wsgi.py
mservices-1.0.21.dist-info/METADATA
mservices-1.0.21.dist-info/WHEEL
mservices-1.0.21.dist-info/top_level.txt
mservices-1.0.21.dist-info/RECORD
